salmon/__init__.py
salmon/building.py
salmon/comparison.py
salmon/expression.py
salmon/model.py
salmon/test.py
salmon/transformation.py
salmon_linear_modeling-1.0.0.dist-info/DESCRIPTION.rst
salmon_linear_modeling-1.0.0.dist-info/METADATA
salmon_linear_modeling-1.0.0.dist-info/RECORD
salmon_linear_modeling-1.0.0.dist-info/WHEEL
salmon_linear_modeling-1.0.0.dist-info/metadata.json
salmon_linear_modeling-1.0.0.dist-info/top_level.txt
