Metadata-Version: 2.0
Name: salmon-linear-modeling
Version: 1.0.0
Summary: A symbolic algebra based linear regression tool.
Home-page: https://github.com/ajboyd2/salmon
Author: Alex Boyd
Author-email: alexjb@uci.edu
License: GPLv3
Download-URL: https://github.com/ajboyd2/salmon/archive/v_100.tar.gz
Keywords: modeling symbolic regression
Platform: UNKNOWN
Classifier: Development Status :: 4 - Beta
Classifier: Intended Audience :: Education
Classifier: Topic :: Scientific/Engineering :: Mathematics
Classifier: License :: OSI Approved :: GNU General Public License v3 (GPLv3)
Classifier: Programming Language :: Python :: 3
Requires-Dist: pandas
Requires-Dist: numpy
Requires-Dist: unittest
Requires-Dist: matplotlib
Requires-Dist: scipy
